app/__init__.py
app/core/__init__.py
app/core/main.py
app/data/__init__.py
app/data/content_owns.csv
app/data/machine_ratings.csv
app/data/machines.csv
app/general_tools/__init__.py
app/general_tools/logger.py
app/postgres/__init__.py
app/postgres/functions.py
app/postgres/table_class.py
app/preprocessing/__init__.py
app/preprocessing/preprocess.py
app/recommendation/__init__.py
app/recommendation/recommendation.py
recommendation_lib-2.1.dist-info/METADATA
recommendation_lib-2.1.dist-info/WHEEL
recommendation_lib-2.1.dist-info/top_level.txt
recommendation_lib-2.1.dist-info/RECORD
