Metadata-Version: 2.1
Name: recommendation_lib
Version: 2.1
Summary: Package containining recommendation algorithm
Author: Giorgos Panagou
Author-email: g.panagou94@gmail.com
Classifier: Programming Language :: Python :: 3
Classifier: Operating System :: OS Independent
Requires-Python: >=3.7
